veto/__init__.py
veto/cli/__init__.py
veto/cli/init.py
veto/cli/templates.py
veto/core/__init__.py
veto/core/history.py
veto/core/interceptor.py
veto/core/validator.py
veto/core/veto.py
veto/custom/__init__.py
veto/custom/client.py
veto/custom/prompt.py
veto/custom/types.py
veto/custom/providers/__init__.py
veto/providers/__init__.py
veto/providers/adapters.py
veto/providers/types.py
veto/rules/__init__.py
veto/rules/prompt.py
veto/rules/types.py
veto/types/__init__.py
veto/types/config.py
veto/types/tool.py
veto/utils/__init__.py
veto/utils/id.py
veto/utils/logger.py
veto-0.1.0.dist-info/METADATA
veto-0.1.0.dist-info/WHEEL
veto-0.1.0.dist-info/entry_points.txt
veto-0.1.0.dist-info/RECORD
