Metadata-Version: 2.4
Name: veto
Version: 0.1.0
Summary: A guardrail system that intercepts and validates AI agent tool calls
License-Expression: MIT
Keywords: agent,ai,anthropic,gemini,guardrail,llm,openai,safety,tool-calls
Requires-Python: >=3.10
Requires-Dist: aiohttp>=3.8.0
Requires-Dist: pyyaml>=6.0
Provides-Extra: all
Requires-Dist: anthropic>=0.20.0; extra == 'all'
Requires-Dist: google-genai>=1.0.0; extra == 'all'
Requires-Dist: openai>=1.0.0; extra == 'all'
Provides-Extra: anthropic
Requires-Dist: anthropic>=0.20.0; extra == 'anthropic'
Provides-Extra: dev
Requires-Dist: mypy>=1.0.0; extra == 'dev'
Requires-Dist: pytest-asyncio>=0.21.0; extra == 'dev'
Requires-Dist: pytest>=7.0.0; extra == 'dev'
Requires-Dist: ruff>=0.4.0; extra == 'dev'
Requires-Dist: types-pyyaml>=6.0.0; extra == 'dev'
Provides-Extra: gemini
Requires-Dist: google-genai>=1.0.0; extra == 'gemini'
Provides-Extra: openai
Requires-Dist: openai>=1.0.0; extra == 'openai'
